{
  "updated": "2026-04-23T15:11:12.668713+00:00",
  "prices": {
    "DOW": {
      "price": 49454.15,
      "change": -33.86,
      "change_pct": -0.0684
    },
    "SP": {
      "price": 7143.05,
      "change": 5.93,
      "change_pct": 0.0831
    },
    "NASDAQ": {
      "price": 24642.42,
      "change": -15.14,
      "change_pct": -0.0614
    },
    "RUT": {
      "price": 2793.92,
      "change": 8.54,
      "change_pct": 0.3068
    },
    "SPY": {
      "price": 711.89,
      "change": 1.42,
      "change_pct": 0.1999
    },
    "QQQ": {
      "price": 656.08,
      "change": 0.61,
      "change_pct": 0.0923
    },
    "IWM": {
      "price": 277.57,
      "change": 1.59,
      "change_pct": 0.5743
    },
    "DIA": {
      "price": 494.43,
      "change": 1.32,
      "change_pct": 0.2681
    },
    "VOO": {
      "price": 654.44,
      "change": 1.29,
      "change_pct": 0.1975
    },
    "YM": {
      "price": 49675.0,
      "change": 357.0,
      "change_pct": 0.7239
    },
    "ES": {
      "price": 7177.0,
      "change": 50.5,
      "change_pct": 0.7086
    },
    "NQ": {
      "price": 27109.75,
      "change": 205.0,
      "change_pct": 0.7619
    },
    "RTY": {
      "price": 2807.1,
      "change": 30.6,
      "change_pct": 1.1021
    },
    "GOLD": {
      "price": 4750.7,
      "change": 30.7,
      "change_pct": 0.6504
    },
    "SILVER": {
      "price": 76.25,
      "change": 0.18,
      "change_pct": 0.2366
    },
    "GLD": {
      "price": 434.29,
      "change": 0.09,
      "change_pct": 0.0207
    },
    "SLV": {
      "price": 68.85,
      "change": -1.31,
      "change_pct": -1.8672
    },
    "BTC": {
      "price": 78122.72,
      "change": -85.83,
      "change_pct": -0.1097
    },
    "ETH": {
      "price": 2328.65,
      "change": -46.44,
      "change_pct": -1.9553
    },
    "IBIT": {
      "price": 44.29,
      "change": -0.04,
      "change_pct": -0.0963
    },
    "ETHA": {
      "price": 17.58,
      "change": -0.36,
      "change_pct": -1.9788
    }
  }
}